life_expectancy/__init__.py
life_expectancy/click_helpers.py
life_expectancy/config.py
life_expectancy/constants.py
life_expectancy/exceptions.py
life_expectancy/helpers.py
life_expectancy/main.py
life_expectancy/data/default_config.ini
pyml_regression_example1-0.1.0.dist-info/METADATA
pyml_regression_example1-0.1.0.dist-info/WHEEL
pyml_regression_example1-0.1.0.dist-info/entry_points.txt
pyml_regression_example1-0.1.0.dist-info/RECORD
