Metadata-Version: 2.3
Name: pyml-regression-example1
Version: 0.1.0
Summary: Python Machine Learning Regression Example: Life Expectancy
Requires-Python: >=3.11
Requires-Dist: click>=8.1.7
Requires-Dist: colorama>=0.4.6
Requires-Dist: matplotlib>=3.9.2
Requires-Dist: numpy>=2.1.1
Requires-Dist: pandas>=2.2.3
Requires-Dist: platformdirs>=4.3.6
Requires-Dist: plotly>=5.24.1
Requires-Dist: pyqt6>=6.7.1
Requires-Dist: scikit-learn>=1.5.2
Requires-Dist: sphinx-autodoc-typehints>=2.0.0
Requires-Dist: sphinx-click-rst-to-ansi-formatter>=0.1.4
